{
  "game_objects": [
    {
      "id": "CardArt_Spell_HoarfrostEffigy",
      "type": "card_art",
      "extensions": {
        "card_art": {
          "shader": "Shiny Shoe/CardEffects",
          "sprite": "SPL_HoarfrostEffigy_01",
          "base_layer": {
            "type": "texture",
            "texture": "SPL_HoarfrostEffigy_01"
          },
          "layers": [
            {
              "type": "moving_texture",
              "texture": "SPL_HoarfrostEffigy_02",
              "linear_speed": {
                "x": 5.0,
                "y": -5.0
              }
            },
            {
              "type": "glow",
              "texture": "MSK_Vignette",
              "mask_texture": "MSK_HoarfrostEffigy_01",
              "tint": {
                "r": 0.947523534,
                "g": 0.580188632,
                "b": 1.0,
                "a": 1.0
              },
              "linear_speed": {
                "x": 12.0,
                "y": 0.0
              }
            }
          ]
        }
      }
    }
  ]
}