{
  "id": "ClassSpikes",
  "guid": "c7e80788-f295-4970-bfdf-5bde2d812eb0",
  "name": "ClassSpikes",
  "regionRunEventPrefabVariant": {
    "m_debugName": "Assets/GameData/Story/Event Prefabs/SoulSavior/Event_SS_Background_BrokenRail.prefab",
    "m_AssetGUID": "4419aa9a6535edf46b5a0a95fb23b9a3"
  },
  "storyId": "ClassSpikes",
  "knotName": "ClassSpikes",
  "numRunsCompletedToSee": 10,
  "priorityTicketCount": 15,
  "numClassesNeededToShow": 3,
  "maxDistanceAllowed": 8,
  "possibleRewards": [
    "Class1SpikeReward",
    "Class2SpikeReward",
    "Class3SpikeReward",
    "Class4SpikeReward",
    "Class5SpikeReward",
    "Class6SpikeReward",
    "Class7SpikeReward",
    "Class8SpikeReward",
    "Class9SpikeReward",
    "Class10SpikeReward",
    "Class11SpikeReward",
    "Class12SpikeReward"
  ]
}