{
  "$schema": "https://github.com/Monster-Train-2-Modding-Group/Trainworks-Reloaded/releases/latest/download/schema.json",
  "relics": [
    {
      "id": "Boss_Railforged_Region4_BossBattle_1",
      "name": "Plaguebringer",
      "type": "sin",
      "extensions": [
        {
          "sin": {
          }
        }
      ],
      "names": {
        "key": "SinsData_nameKey-b9151519e91140ce-170b467b2fd43c84e9d610b0d2635d9d-v2",
        "english": "Plaguebringer",
        "french": "Porteur de peste",
        "german": "Pestbringer",
        "russian": "Разносчик заразы",
        "portuguese": "Portador da Praga",
        "chinese": "瘟疫使者",
        "spanish": "Heraldo de la plaga",
        "chinese_traditional": "瘟疫散播者",
        "korean": "역병의 전령",
        "japanese": "疫病をもたらす者"
      },
      "descriptions": {
        "key": "SinsData_descriptionKey-fb175845c992afa3-170b467b2fd43c84e9d610b0d2635d9d-v2",
        "english": "Gain [duality] at [effect0.power]% health.",
        "french": "Octroie [duality] à <nobr>[effect0.power] %</nobr> de PV.",
        "german": "Erhalte [duality] bei [effect0.power] % Gesundheit.",
        "russian": "Дает [duality] если при [effect0.power]% здоровья.",
        "portuguese": "Recebe [duality] com [effect0.power]% de vida.",
        "chinese": "生命值为 [effect0.power]% 时，获得 [duality]。",
        "spanish": "Añade [duality] con [effect0.power] % de salud.",
        "chinese_traditional": "在[effect0.power]%生命值時獲得[duality]。",
        "korean": "체력이 [effect0.power]%일 때 [duality]을 획득합니다.",
        "japanese": "体力[effect0.power]%到達時に[duality]を得る。"
      },
      "relic_effects": [
        "@Boss_Railforged_Region4_BossBattle_1.effects0"
      ]
    }
  ],
  "relic_effects": [
    {
      "id": "Boss_Railforged_Region4_BossBattle_1.effects0",
      "name": "RelicEffectNull",
      "param_int": 50
    }
  ]
}