{
  "$schema": "https://github.com/Monster-Train-2-Modding-Group/Trainworks-Reloaded/releases/latest/download/schema.json",
  "cards": [
    {
      "id": "PenitentsDeathsuit",
      "names": {
        "key": "CardData_nameKey-1f37a1b17fe66c5f-09cb7d90f06b29b40a3da01941c54bf3-v2",
        "english": "Penitent's Deathsuit",
        "french": "Armure funeste de pénitent",
        "german": "Todesanzug des Büßers",
        "russian": "Костюм покаяния смертью",
        "portuguese": "Traje Mortal do Penitente",
        "chinese": "虔信者的死亡之衣",
        "spanish": "Traje letal del penitente",
        "chinese_traditional": "懺悔者的死鬥服",
        "korean": "참회자의 죽음의 갑옷",
        "japanese": "悔悟者の死装束"
      },
      "descriptions": {
        "key": "CardData_overrideDescriptionKey-6f87287d03b90d0d-09cb7d90f06b29b40a3da01941c54bf3-v2",
        "english": "Can be equipped on enemy units.",
        "french": "Équipement possible sur les ennemis.",
        "german": "Kann gegnerischen Einheiten angelegt werden.",
        "russian": "Можно использовать на врагах.",
        "portuguese": "Pode ser equipado em unidades inimigas.",
        "chinese": "可以装备在敌方单位上。",
        "spanish": "Se puede equipar en unidades enemigas.",
        "chinese_traditional": "可以裝備在敵方單位上。",
        "korean": "적 유닛에 장착할 수 있습니다.",
        "japanese": "敵ユニットに装着可能。"
      },
      "lore_tooltips": [
        {
          "key": "CardData_data-4b56f34d02477d41-09cb7d90f06b29b40a3da01941c54bf3-v2",
          "english": "“No angel could survive this device. And I was the monster who created it. Perhaps I truly was more a demon now.”\n—Finna the Doomed",
          "french": "<nobr>« Aucun</nobr> ange ne pourrait survivre à cet appareil. Le monstre qui l'a créé, c'est moi. Peut-être étais-je encore plus démoniaque à <nobr>l'époque. »</nobr> \n— Finna la Condamnée",
          "german": "„Kein Engel kann diesen Apparat überleben. Und ich bin das Monster, das ihn erschuf. Vielleicht war ich tatsächlich ein Dämon.“\n—Finna die Verdammte",
          "russian": "«Ни один ангел не выжил в этом костюме, и изобрела его именно я. Пожалуй, так я стала скорее демоном, чем ангелом».\n— Финна Обреченная",
          "portuguese": "“Nenhum anjo poderia sobreviver a esse dispositivo. E eu fui o monstro que o criou. Acho que, no fundo, sempre tive um demônio interno.”\n— Finna, a Condenada",
          "chinese": "“没有天使能在这套装置中幸存。而我就是创造它的怪物。也许我现在更像是一个恶魔。”\n——命运已定的菲娜",
          "spanish": "«Ningún ángel podría sobrevivir a este dispositivo, y yo fui el monstruo que lo creó. Quizá ahora esté más cerca de los demonios».\n—Finna la Condenada",
          "chinese_traditional": "「沒有天使能在這個裝置下存活。而我就是創造它的怪物。也許我現在真的更像個惡魔了。」\n——『絕命者』費納",
          "korean": "“이걸 입고 살아남은 천사는 하나도 없었다. 그걸 만든 건 나였다. 아마도 이제 난 악마와 다를 바 없을 것이다.”\n- 파멸자 피나",
          "japanese": "「この装置から逃れられる天使はいないだろう。そしてこれを作り出した化け物は私なのだ。私は真に悪魔と化したのかもしれない」\n—絶望のフィナ"
        }
      ],
      "cost": 1,
      "card_type": "equipment",
      "rarity": "uncommon",
      "class": "ClassBanished",
      "pools": [
        "EquipmentMergeIgnore",
        "EquipmentPool",
        "EquipmentPoolEnemy",
        "MegaPool",
        "UnitsBanishedBannerReplacementMutator"
      ],
      "card_art": {
        "asset_name": "Assets/GameData/CardArt/Portrait_Prefabs/CardArt_Spell_PenitentsDeathsuit.prefab",
        "asset_guid": "f4778dee2d13be246ba6647847eff7a0"
      },
      "effects": [
        "@PenitentsDeathsuit.effects0"
      ],
      "targetless": false,
      "unlock_level": 7,
      "initial_keyboard_target": "front_enemy",
      "artist": "Aaron Lovett"
    }
  ],
  "effects": [
    {
      "id": "PenitentsDeathsuit.effects0.paramCardUpgradeData.triggerUpgrades0.effects0",
      "name": "CardEffectAddStatusEffect",
      "target_mode": "self",
      "param_status_effects": [
        {
          "status": "melee weakness",
          "count": 1
        }
      ]
    },
    {
      "id": "PenitentsDeathsuit.effects0",
      "name": "CardEffectAttachEquipment",
      "target_mode": "drop_target_character",
      "target_team": "both",
      "param_upgrade": "PenitentShiftGainWeakness",
      "applied_vfx": "@PenitentsDeathsuit.effects0.appliedVFX"
    }
  ],
  "vfxs": [
    {
      "id": "PenitentsDeathsuit.effects0.appliedVFX",
      "vfx_prefab_ref_left": {
        "asset_name": "Assets/VFX/Equipment/PenitentsDeathsuit/FX_PenitentsDeathsuit_Parent.prefab",
        "asset_guid": "d092493d27ab6e146a3278d9705df482"
      },
      "spawn_location": "character_center"
    }
  ]
}