{
  "id": "Covenant00_FTUE",
  "name": "Covenant00_FTUE",
  "effects": [
    {
      "relicEffectClassName": "RelicEffectModifyCharacterMaxHealth",
      "paramSourceTeam": "heroes",
      "paramInt": 250,
      "paramCharacterSubtype": "SubtypesData_BossT2_935b30b5-bb94-4fd4-b3be-2ed0eb73ccf6",
      "paramTrigger": "on_spawn"
    },
    {
      "relicEffectClassName": "RelicEffectModifyCharacterMaxHealth",
      "paramSourceTeam": "heroes",
      "paramInt": 375,
      "paramCharacterSubtype": "SubtypesData_BossT3_ef0103da-a050-4ebb-af3a-b3e285db5e0c",
      "paramTrigger": "on_spawn"
    },
    {
      "relicEffectClassName": "RelicEffectModifyCharacterMaxHealth",
      "paramSourceTeam": "heroes",
      "paramInt": 30,
      "paramCharacterSubtype": "SubtypesData_HeavyT2",
      "paramTrigger": "on_spawn"
    },
    {
      "relicEffectClassName": "RelicEffectModifyCharacterMaxHealth",
      "paramSourceTeam": "heroes",
      "paramInt": 50,
      "paramCharacterSubtype": "SubtypesData_HeavyT3",
      "paramTrigger": "on_spawn"
    },
    {
      "relicEffectClassName": "RelicEffectModifyCharacterAttackDamage",
      "paramCardType": "invalid",
      "paramSourceTeam": "heroes",
      "paramInt": 1,
      "paramCharacterSubtype": "SubtypesData_AttackerT2",
      "paramTrigger": "on_spawn"
    },
    {
      "relicEffectClassName": "RelicEffectModifyCharacterAttackDamage",
      "paramCardType": "invalid",
      "paramSourceTeam": "heroes",
      "paramInt": 1,
      "paramCharacterSubtype": "SubtypesData_AttackerT3",
      "paramTrigger": "on_spawn"
    },
    {
      "relicEffectClassName": "RelicEffectModifyCharacterAttackDamage",
      "paramCardType": "invalid",
      "paramSourceTeam": "heroes",
      "paramInt": 3,
      "paramCharacterSubtype": "SubtypesData_BossT2_935b30b5-bb94-4fd4-b3be-2ed0eb73ccf6",
      "paramTrigger": "on_spawn"
    },
    {
      "relicEffectClassName": "RelicEffectModifyCharacterAttackDamage",
      "paramCardType": "invalid",
      "paramSourceTeam": "heroes",
      "paramInt": 5,
      "paramCharacterSubtype": "SubtypesData_BossT3_ef0103da-a050-4ebb-af3a-b3e285db5e0c",
      "paramTrigger": "on_spawn"
    },
    {
      "relicEffectClassName": "RelicEffectModifyCharacterMaxHealth",
      "paramSourceTeam": "heroes",
      "paramInt": 600,
      "paramCharacterSubtype": "SubtypesData_BigBoss2_e3e6f1a2-34a7-4493-b9d7-a123e182241e",
      "paramTrigger": "on_spawn"
    },
    {
      "relicEffectClassName": "RelicEffectModifyCharacterMaxHealth",
      "paramSourceTeam": "heroes",
      "paramInt": 1000,
      "paramCharacterSubtype": "SubtypesData_BigBossT3_f7449215-5071-4671-909c-a02e2cceb821",
      "paramTrigger": "on_spawn"
    },
    {
      "relicEffectClassName": "RelicEffectModifyCharacterMaxHealth",
      "paramSourceTeam": "heroes",
      "paramInt": 1000,
      "paramCharacterSubtype": "SubtypesData_BigBossT3_f7449215-5071-4671-909c-a02e2cceb821",
      "paramTrigger": "on_spawn"
    }
  ],
  "ascensionLevel": 1,
  "hellforgedDescriptionKey": "Covenant1_Description_Hellforged"
}