{
  "id": "SoulSavior_RunDistance4",
  "name": "Run Distance 4",
  "nameKey": {
    "key": "MutatorData_nameKey-85fd897006caeafd-4ecc43ffb0c04134abf625f1b841a078-v2",
    "english": "Run Distance 4",
    "french": "Distance de la partie 4",
    "german": "Reisedistanz 4",
    "russian": "Длина маршрута 4",
    "portuguese": "Distância de Corrida 4",
    "chinese": "一轮距离 4",
    "spanish": "Distancia de partida 4",
    "chinese_traditional": "闖關距離4",
    "korean": "여정 거리 4",
    "japanese": "運行距離4"
  },
  "effects": [
    {
      "relicEffectClassName": "RelicEffectScaleStatusApplicationsOnSpawn",
      "paramStatusEffects": [
        {
          "statusId": "buff",
          "count": 0
        },
        {
          "statusId": "hivemind",
          "count": 0
        },
        {
          "statusId": "burst",
          "count": 0
        },
        {
          "statusId": "malaise",
          "count": 0
        },
        {
          "statusId": "corruption",
          "count": 0
        },
        {
          "statusId": "decay",
          "count": 0
        },
        {
          "statusId": "debuff",
          "count": 0
        },
        {
          "statusId": "witherbloom",
          "count": 0
        }
      ],
      "paramFloat": 1.2,
      "paramBool": true,
      "paramBool2": true,
      "paramBool3": true,
      "notificationSuppressed": true
    },
    {
      "relicEffectClassName": "RelicEffectIncreasePyreHealth",
      "paramInt2": 2,
      "notificationSuppressed": true
    },
    {
      "relicEffectClassName": "RelicEffectIncreasePyreAttack",
      "paramInt2": 2,
      "notificationSuppressed": true
    }
  ],
  "isHidden": true,
  "disableInDailyChallenges": true,
  "isSoulSaviorModeOnly": true
}