{
  "id": "ValorTransferOnAngelDeath",
  "guid": "8c493cd7-8048-4598-bdd5-6cc2801cd842",
  "name": "Karmic Censer",
  "nameKey": {
    "key": "CollectableRelicData_nameKey-e8416cc3cd8f46de-87da24bdc15a38643a1d6426b7c3bbe9-v2",
    "english": "Karmic Censer",
    "french": "Encensoir karmique",
    "german": "Karma-Rauchfass",
    "russian": "Кармическое кадило",
    "portuguese": "Incensário Cármico",
    "chinese": "命运香炉",
    "spanish": "Incensario kármico",
    "chinese_traditional": "業力香爐",
    "korean": "업보의 향로",
    "japanese": "因果の香炉"
  },
  "descriptionKey": {
    "key": "CollectableRelicData_descriptionKey-9284a3afd1e7a4d3-87da24bdc15a38643a1d6426b7c3bbe9-v2",
    "english": "[shift] triggers an additional time.",
    "french": "Déclenche [shift] une fois de plus.",
    "german": "[shift] wird ein weiteres Mal ausgelöst.",
    "russian": "[shift] срабатывает еще раз.",
    "portuguese": "[shift] aciona tempo adicional.",
    "chinese": "[shift] 额外触发一次。",
    "spanish": "El [shift] se activa una vez más.",
    "chinese_traditional": "[shift]額外觸發一次。",
    "korean": "[shift] 효과가 한 번 더 발생합니다.",
    "japanese": "[shift]が追加で発動する。"
  },
  "relicLoreTooltipKeys": [
    {
      "key": "CollectableRelicData_data-6bb77d9429323d34-87da24bdc15a38643a1d6426b7c3bbe9-v2",
      "english": "“Why does this smell like chocolate?” asked Fel. “What’s chocolate?” asked Talos.",
      "french": "<nobr>« Pourquoi</nobr> ça sent le <nobr>chocolat ? »</nobr> demanda Fel. <nobr>« C'est</nobr> quoi, le <nobr>chocolat ? »</nobr> demanda Talos.",
      "german": "„Warum riecht es hier nach Schokolade?“, fragte Fel. „Was ist Schokolade?“, erwiderte Talos.",
      "russian": "«И почему от него пахнет шоколадом?» — задумалась Фэл. «А что такое шоколад?» — спросила Талос.",
      "portuguese": "“Por que isso tem cheiro de chocolate?”, perguntou Fel. “O que é chocolate?”, perguntou Talos.",
      "chinese": "“为什么这闻起来像巧克力？”菲尔问道。“巧克力是什么？”塔洛丝问道。",
      "spanish": "«¿Y esto por qué huele a chocolate?», preguntó Fel. «¿Qué es el chocolate?», preguntó Talos.",
      "chinese_traditional": "「這為什麼聞起來像巧克力？」費爾問道。「什麼是巧克力？」塔洛斯問道。",
      "korean": "“어째서 초콜릿 냄새가 나지?” 펠이 물었다. “초콜릿이 뭔데?” 탈로스가 물었다.",
      "japanese": "「これはなぜチョコレートの香りがするの？」とフェルが聞くと、「チョコレートって何？」とタロスが聞き返した。"
    }
  ],
  "rarity": "common",
  "linkedClass": "ClassBanished",
  "pools": [
    "MegaRelicPool"
  ],
  "effects": [
    {
      "relicEffectClassName": "RelicEffectModifyTriggerCount",
      "paramInt": 1,
      "paramBool2": true,
      "paramTrigger": "on_shift"
    }
  ],
  "unlockLevel": 8
}