{
  "$schema": "https://github.com/Monster-Train-2-Modding-Group/Trainworks-Reloaded/releases/latest/download/schema.json",
  "relics": [
    {
      "id": "BalatroEventPerkeo",
      "type": "collectable",
      "extensions": [
        {
          "collectable": {
            "rarity": "champion",
            "from_story_event": true,
            "force_update_count_label": true
          }
        }
      ],
      "names": {
        "key": "CollectableRelicData_nameKey-494a8f3e41639521-53d48e2bfe68aa54286f07927151f94b-v2",
        "english": "Perkeo",
        "french": "Perkeo",
        "german": "Perkeo",
        "russian": "Перкео",
        "portuguese": "Perkeo",
        "chinese": "帕奇欧",
        "spanish": "Perkeo",
        "chinese_traditional": "佩爾基",
        "korean": "페르케오",
        "japanese": "ペルケオ"
      },
      "descriptions": {
        "key": "CollectableRelicData_descriptionKey-cfbad99a271766de-53d48e2bfe68aa54286f07927151f94b-v2",
        "english": "At the start of battle, gain a <b>Calcified Ember</b> that converts to <b>Excavated Ember</b> after not playing it once.",
        "french": "Au début du combat, gagnez une <b>Braise calcifiée</b> qui se convertit en <b>Braise déterrée</b> après ne pas l'avoir jouée une fois.",
        "german": "Erhalte zu Beginn des Kampfes <b>Verkalkte Glutasche</b>, die sich in <b>Freigelegte Glutasche</b> verwandelt, wenn du sie nicht ausspielst.",
        "russian": "В начале боя дает <b>застывший уголь</b>, который, если его не использовать, превратится в <b>добытый</b>.",
        "portuguese": "No início da batalha, ganha uma <b>Brasa Calcificada</b> que se converte em <b>Brasa Escavada</b> depois de não ser usada nenhuma vez.",
        "chinese": "在战斗开始时，获得一张<b>钙化的余烬</b>，一回合后未使用则变为<b>采掘的余烬</b>。",
        "spanish": "Al principio de la batalla recibes un <b>Ascua calcificada</b> que se convierte en <b>Ascua extraída</b> tras no jugarla.",
        "chinese_traditional": "在戰鬥開始時，獲得一個<b>鈣化的餘燼</b>，在經過一回合且沒有打出後轉變為<b>挖掘出的餘燼</b>。",
        "korean": "전투 시작 시, <b>굳어진 잔불</b>을 획득하며, 이를 한 번도 사용하지 않으면 <b>발굴한 잔불</b>로 변환됩니다.",
        "japanese": "バトルの開始時に、1度プレイせずにいると<b>採掘エンバー</b>に変換される<b>石灰化エンバー</b>を得る。"
      },
      "lore_tooltips": [
        {
          "key": "CollectableRelicData_data-e605de0a71a1c4b2-53d48e2bfe68aa54286f07927151f94b-v2",
          "english": "“Why so serious?”",
          "french": "<nobr>« Pourquoi</nobr> tant de <nobr>sérieux ? »</nobr>",
          "german": "„Warum so ernst?“",
          "russian": "«Че ты такой серьезный?»",
          "portuguese": "“Por que está tão sério?”",
          "chinese": "“干嘛这么严肃？”",
          "spanish": "«¿Por qué tan serio?».",
          "chinese_traditional": "「為什麼這麼認真？」",
          "korean": "“뭐가 그리 심각하지?”",
          "japanese": "「もっと肩の力抜きなよ」"
        }
      ],
      "relic_effects": [
        "@BalatroEventPerkeo.effects0"
      ]
    }
  ],
  "relic_effects": [
    {
      "id": "BalatroEventPerkeo.effects0",
      "name": "RelicEffectAddCardsStartOfBattle",
      "additional_tooltips": [
        "@BalatroEventPerkeo.effects0.additionalTooltips0"
      ],
      "param_upgrade": "CalcifiedEmberConvert",
      "param_bool_2": true,
      "param_card_pool": "CalcifiedEmberOnlyPool"
    }
  ],
  "effects": [
    {
      "id": "BalatroEventPerkeo.effects0.paramCardUpgradeData.cardTriggerUpgrades0.cardEffects0.paramCardData.effects0",
      "name": "CardEffectGainEnergy",
      "param_int": 2
    },
    {
      "id": "BalatroEventPerkeo.effects0.paramCardUpgradeData.cardTriggerUpgrades0.cardEffects0.paramCardData.effects1",
      "name": "CardEffectDraw",
      "param_int": 1
    },
    {
      "id": "BalatroEventPerkeo.effects0.paramCardUpgradeData.cardTriggerUpgrades0.cardEffects0",
      "name": "CardEffectBalatroConvertCard",
      "param_card": "@BalatroEventPerkeo.effects0.paramCardUpgradeData.cardTriggerUpgrades0.cardEffects0.paramCardData",
      "param_int": 1
    }
  ],
  "additional_tooltips": [
    {
      "id": "BalatroEventPerkeo.effects0.additionalTooltips0",
      "descriptions": {
        "key": "Trigger_OnUnplayed_TooltipText",
        "english": "Triggers if this card remains in hand at the end of the turn.",
        "french": "Se déclenche si cette carte est restée dans la main à la fin du tour.",
        "german": "Wird ausgelöst, wenn diese Karte sich am Ende des Zuges noch auf der Hand befindet.",
        "russian": "Срабатывает, если эта карта остается в руке в конце хода.",
        "portuguese": "Desencadeia se esta carta permanecer em sua mão ao fim do turno.",
        "chinese": "若你的回合结束时，这张卡牌依然在你的手牌中，则在回合结束时触发。",
        "spanish": "Se activa si esta carta se mantiene en la mano al final del turno.",
        "chinese_traditional": "如果這張卡牌在回合結束時仍在手牌中則觸發。",
        "korean": "턴이 끝날 때까지 이 카드가 패에 남아 있으면 효과가 발동합니다.",
        "japanese": "ターンの終了時に、このカードが手札に残されていると発動する。"
      },
      "titles": {
        "key": "Trigger_OnUnplayed_CardText",
        "english": "Reserve",
        "french": "Réserve",
        "german": "Behalten",
        "russian": "Резерв",
        "portuguese": "Reservar",
        "chinese": "保存",
        "spanish": "Reserva",
        "chinese_traditional": "保留",
        "korean": "남김패",
        "japanese": "リザーブ"
      },
      "style": "trigger"
    }
  ]
}